tfra_nightly-0.8.1.dev20250104050516.dist-info/RECORD
tfra_nightly-0.8.1.dev20250104050516.dist-info/LICENSE
tfra_nightly-0.8.1.dev20250104050516.dist-info/WHEEL
tfra_nightly-0.8.1.dev20250104050516.dist-info/top_level.txt
tfra_nightly-0.8.1.dev20250104050516.dist-info/METADATA
tensorflow_recommenders_addons/conftest.py
tensorflow_recommenders_addons/version.py
tensorflow_recommenders_addons/register.py
tensorflow_recommenders_addons/__init__.py
tensorflow_recommenders_addons/tests/__init__.py
tensorflow_recommenders_addons/utils/test_utils.py
tensorflow_recommenders_addons/utils/__init__.py
tensorflow_recommenders_addons/utils/types.py
tensorflow_recommenders_addons/utils/check_platform.py
tensorflow_recommenders_addons/utils/resource_loader.py
tensorflow_recommenders_addons/utils/ensure_tf_install.py
tensorflow_recommenders_addons/dynamic_embedding/__init__.py
tensorflow_recommenders_addons/dynamic_embedding/core/_math_ops.so
tensorflow_recommenders_addons/dynamic_embedding/core/_cuckoo_hashtable_ops.so
tensorflow_recommenders_addons/dynamic_embedding/core/_data_flow_ops.so
tensorflow_recommenders_addons/dynamic_embedding/core/_redis_table_ops.so
tensorflow_recommenders_addons/dynamic_embedding/python/__init__.py
tensorflow_recommenders_addons/dynamic_embedding/python/keras/models.py
tensorflow_recommenders_addons/dynamic_embedding/python/keras/__init__.py
tensorflow_recommenders_addons/dynamic_embedding/python/keras/callbacks.py
tensorflow_recommenders_addons/dynamic_embedding/python/keras/layers/embedding.py
tensorflow_recommenders_addons/dynamic_embedding/python/keras/layers/__init__.py
tensorflow_recommenders_addons/dynamic_embedding/python/keras/layers/dynamic_layer_normalization.py
tensorflow_recommenders_addons/dynamic_embedding/python/train/checkpoint.py
tensorflow_recommenders_addons/dynamic_embedding/python/train/__init__.py
tensorflow_recommenders_addons/dynamic_embedding/python/train/saver.py
tensorflow_recommenders_addons/dynamic_embedding/python/ops/tf_save_restore_patch.py
tensorflow_recommenders_addons/dynamic_embedding/python/ops/warm_start_util.py
tensorflow_recommenders_addons/dynamic_embedding/python/ops/ragged_embedding_ops.py
